surverse/__init__.py
surverse-0.1.0.dist-info/METADATA
surverse-0.1.0.dist-info/WHEEL
surverse-0.1.0.dist-info/RECORD
