Metadata-Version: 2.1
Name: surverse
Version: 0.1.0
Summary: A comprehensive toolkit for survival analysis in Python
Author: Yajie Zhu
Author-email: yajiez.me@gmail.com
Requires-Python: >=3.11,<4.0
Classifier: Programming Language :: Python :: 3
Classifier: Programming Language :: Python :: 3.11
Classifier: Programming Language :: Python :: 3.12
Requires-Dist: ipykernel (>=6.29.5,<7.0.0)
Requires-Dist: lifelines (>=0.30.0,<0.31.0)
Requires-Dist: pandas (>=2.2.3,<3.0.0)
Requires-Dist: scikit-learn (>=1.5.2,<2.0.0)
Requires-Dist: seaborn (>=0.13.2,<0.14.0)
Requires-Dist: torch (>=2.5.1,<3.0.0)
Requires-Dist: xgboost (>=2.1.2,<3.0.0)
